{
    "videoId": "eG_Ttkrz-ag",
    "history": [
        {
            "fetchedAt": "20260219_172744",
            "commentCount": 0,
            "comments": []
        },
        {
            "fetchedAt": "20260221_080603",
            "commentCount": 2,
            "comments": [
                {
                    "text": "Ya Allah Hu Allah Hu Allah Hu dil mein likhate\u2764 hak Mohammed soch Mohammed ya Mohammed",
                    "author": "@WaseemChef-e4t",
                    "likes": 0,
                    "publishedAt": "2026-02-20T17:46:12Z"
                },
                {
                    "text": "\u0627\u0686\u0627\u06c1\u0648\u0627\u06d4\u06cc\u06c1\u06d4\u0644\u0648\u06af\u06d4\u06c1\u06d2\u06d4\u0648\u06c1\u06d4\u0628\u06be\u06cc\u06d4\u0645\u06cc\u0688\u06cc\u0627\u067e\u0631\u06d4\n\u0628\u0648\u0631\u0627\u06c1\u0648\u0622\u06d4\u06c1\u0648\u0627\u062a\u0648\u0646\u06c1\u06cc\u06d4\u06d4\u06d4\u06d4\u06d4\u06d4\u06d4\u06d4\u06d4\u06d4\u0688\u0648\u0632\u0648\u0645\u06cc\u06ba\u06d4\u0627\u06cc\u06a9\u06d4\u0646\u0645\u0628\u0631\u06c1\u06d2",
                    "author": "@MuzafirHussain-n9g9x",
                    "likes": 0,
                    "publishedAt": "2026-02-21T05:38:10Z"
                }
            ]
        }
    ]
}