{
    "videoId": "wcU8P8rkeMA",
    "history": [
        {
            "fetchedAt": "20260214_212228",
            "commentCount": 2,
            "comments": [
                {
                    "text": "Nice",
                    "author": "@meenaartsandcrafts",
                    "likes": 1,
                    "publishedAt": "2026-02-14T15:22:44Z"
                },
                {
                    "text": "\u2764",
                    "author": "@sohel.k2471",
                    "likes": 0,
                    "publishedAt": "2026-02-14T18:40:19Z"
                }
            ]
        }
    ]
}