{
    "videoId": "y40Z8Dp5E8Q",
    "history": [
        {
            "fetchedAt": "20260212_005218",
            "commentCount": 1,
            "comments": [
                {
                    "text": "This is not good advice.",
                    "author": "@LifeisFallingONtheCouch",
                    "likes": 1,
                    "publishedAt": "2026-02-11T20:22:34Z"
                }
            ]
        },
        {
            "fetchedAt": "20260212_005557",
            "commentCount": 1,
            "comments": [
                {
                    "text": "This is not good advice.",
                    "author": "@LifeisFallingONtheCouch",
                    "likes": 1,
                    "publishedAt": "2026-02-11T20:22:34Z"
                }
            ]
        },
        {
            "fetchedAt": "20260214_041537",
            "commentCount": 2,
            "comments": [
                {
                    "text": "Not sure what that accomplished!",
                    "author": "@IceSk8Princessa12",
                    "likes": 1,
                    "publishedAt": "2026-02-14T02:36:10Z"
                },
                {
                    "text": "This is not good advice.",
                    "author": "@LifeisFallingONtheCouch",
                    "likes": 2,
                    "publishedAt": "2026-02-11T20:22:34Z"
                }
            ]
        }
    ]
}