{
    "videoId": "hjNmcq6kjk0",
    "history": [
        {
            "fetchedAt": "20260214_212217",
            "commentCount": 0,
            "comments": []
        },
        {
            "fetchedAt": "20260216_191236",
            "commentCount": 1,
            "comments": [
                {
                    "text": "Bhai freefire player tha pahle \ud83d\ude22\ud83d\ude22\ud83d\ude22",
                    "author": "@Rambo.3d.1k",
                    "likes": 1,
                    "publishedAt": "2026-02-16T10:11:25Z"
                }
            ]
        }
    ]
}