{
    "videoId": "lVpEFoPSmJc",
    "history": [
        {
            "fetchedAt": "20260212_005613",
            "commentCount": 17,
            "comments": [
                {
                    "text": "Contexto: Es una referencia a lo que paso en un stream de rimworld. \nclip:\n\n https://www.youtube.com/shorts/1hHUzfhe2gA",
                    "author": "@somarda",
                    "likes": 122,
                    "publishedAt": "2026-02-11T20:28:55Z"
                },
                {
                    "text": "Ahora necesitamos un stream recreando las guerras gay.",
                    "author": "@juliopoche6715",
                    "likes": 23,
                    "publishedAt": "2026-02-11T21:07:18Z"
                },
                {
                    "text": "C\u00f3mo de dura estuvo la guerra gay que se muri\u00f3 gente \ud83e\udd75",
                    "author": "@ArturiasPe",
                    "likes": 14,
                    "publishedAt": "2026-02-11T21:22:05Z"
                },
                {
                    "text": "\ud83d\udc80\ud83e\udef5\ud83c\udfff\ud83d\uddff mi padre muri\u00f3 , en las guerras gays ! \n\n\ud83d\ude14\ud83e\udd1d\ud83d\ude29",
                    "author": "@Nohumn",
                    "likes": 57,
                    "publishedAt": "2026-02-11T20:36:46Z"
                },
                {
                    "text": "Yo siempre tengo un colono medio pocho, sobrevive unicamente para limpiar la base y transportar cosas",
                    "author": "@coachrotatoria",
                    "likes": 45,
                    "publishedAt": "2026-02-11T21:07:47Z"
                },
                {
                    "text": "En las Guerras Gay peleo Obi Wan Queernobi",
                    "author": "@joaquinhunziker3974",
                    "likes": 12,
                    "publishedAt": "2026-02-11T21:00:19Z"
                },
                {
                    "text": "T\u00edtulo alternativo:Wider recibe una paliza por basado.",
                    "author": "@xincognita13imcomprendido65",
                    "likes": 3,
                    "publishedAt": "2026-02-11T21:33:51Z"
                },
                {
                    "text": "Por un momento crei que terminaria con todos apoyandolo y el sujeto tratando de explicar que no era por eso",
                    "author": "@zantory9810",
                    "likes": 7,
                    "publishedAt": "2026-02-11T20:38:15Z"
                },
                {
                    "text": "Yo lo rechazaba por la \"Dependencia al Yayo\". En mi colonia no acepto a alguien que acapare o consuma de la mercanc\u00eda. XD",
                    "author": "@YogTherion",
                    "likes": 1,
                    "publishedAt": "2026-02-11T21:52:05Z"
                },
                {
                    "text": "Yo pense que lo rechazar\u00edan por no poder reproducirse o algo asi",
                    "author": "@julianparedesvillar4852",
                    "likes": 3,
                    "publishedAt": "2026-02-11T20:40:23Z"
                },
                {
                    "text": "Yo ten\u00eda un vampiro homosexual, hijosumadre se la pasaba deprimido porque todos los dem\u00e1s colonos lo rechazaban",
                    "author": "@sinenominenilh2223",
                    "likes": 1,
                    "publishedAt": "2026-02-11T23:02:54Z"
                },
                {
                    "text": "Pues todo lo dem\u00e1s para somarda es perfectamente pasable y con el can\u00edbal encajar bien con somarda",
                    "author": "@Emilianotoro20",
                    "likes": 3,
                    "publishedAt": "2026-02-11T20:41:44Z"
                },
                {
                    "text": "En esta colonia aceptamos: Asesinos, psic\u00f3pata, delincuentes y can\u00edbales, pero nunca homofobicos",
                    "author": "@alex-in1sb",
                    "likes": 0,
                    "publishedAt": "2026-02-11T22:01:25Z"
                },
                {
                    "text": "Pir\u00f3mano, Can\u00edbal, Gay, Adicto al Yayo y encima incapaz de violencia.",
                    "author": "@The_Last_Sollist",
                    "likes": 2,
                    "publishedAt": "2026-02-11T21:32:23Z"
                },
                {
                    "text": "En las guerras cuando?",
                    "author": "@dantedevil1401",
                    "likes": 0,
                    "publishedAt": "2026-02-12T00:31:51Z"
                },
                {
                    "text": "Wider:",
                    "author": "@JCBT",
                    "likes": 0,
                    "publishedAt": "2026-02-11T20:40:18Z"
                },
                {
                    "text": "Hace poco me atacaron en una partida...capture a un tipo nomas para sacarle sangre, cuando revise era homosexual.\n As\u00ed que le corte ambas piernas, ambos brazos, actualmente es una fuente de sangre confiable y sumisa \ud83d\udeac\ud83d\uddff\ud83d\udd25\ud83c\udde9\ud83c\uddea",
                    "author": "@salamankax_9722",
                    "likes": 3,
                    "publishedAt": "2026-02-11T20:44:38Z"
                }
            ]
        }
    ]
}