{
    "videoId": "eFZrXIM9oIg",
    "history": [
        {
            "fetchedAt": "20260214_041647",
            "commentCount": 0,
            "comments": []
        },
        {
            "fetchedAt": "20260214_085023",
            "commentCount": 1,
            "comments": [
                {
                    "text": "Nice videos \ud83c\udf89",
                    "author": "@MuhammedYousuf-t8s",
                    "likes": 0,
                    "publishedAt": "2026-02-14T05:59:02Z"
                }
            ]
        },
        {
            "fetchedAt": "20260214_212155",
            "commentCount": 3,
            "comments": [
                {
                    "text": "\u2764\u2764\u2764\ud83c\udf89\ud83c\udf89\ud83c\udf89\ud83c\udf89\ud83c\udf89",
                    "author": "@Aasiyaa-m8v",
                    "likes": 2,
                    "publishedAt": "2026-02-14T09:11:09Z"
                },
                {
                    "text": "Bada bada bahut achcha Karen",
                    "author": "@Krishna_Gamer_24T",
                    "likes": 0,
                    "publishedAt": "2026-02-14T13:23:51Z"
                },
                {
                    "text": "Nice videos \ud83c\udf89",
                    "author": "@MuhammedYousuf-t8s",
                    "likes": 0,
                    "publishedAt": "2026-02-14T05:59:02Z"
                }
            ]
        }
    ]
}