{
    "videoId": "0a5XRBfNrlo",
    "history": [
        {
            "fetchedAt": "20260213_210859",
            "commentCount": 0,
            "comments": []
        },
        {
            "fetchedAt": "20260214_041633",
            "commentCount": 1,
            "comments": [
                {
                    "text": "\ud83d\ude05I'll look",
                    "author": "@KapilKumari-dv5ct",
                    "likes": 2,
                    "publishedAt": "2026-02-14T00:56:52Z"
                }
            ]
        },
        {
            "fetchedAt": "20260214_212139",
            "commentCount": 2,
            "comments": [
                {
                    "text": "\u2764\u2764\u2764",
                    "author": "@FreefirMafia",
                    "likes": 2,
                    "publishedAt": "2026-02-14T13:43:34Z"
                },
                {
                    "text": "\ud83d\ude05I'll look",
                    "author": "@KapilKumari-dv5ct",
                    "likes": 12,
                    "publishedAt": "2026-02-14T00:56:52Z"
                }
            ]
        },
        {
            "fetchedAt": "20260215_143427",
            "commentCount": 5,
            "comments": [
                {
                    "text": "\ud83c\udf89\ud83d\ude22\ud83d\ude2e\ud83d\ude05\ud83d\ude0a",
                    "author": "@As-jz6to",
                    "likes": 0,
                    "publishedAt": "2026-02-15T14:27:52Z"
                },
                {
                    "text": "\u2764\u2764\u2764",
                    "author": "@FreefirMafia",
                    "likes": 5,
                    "publishedAt": "2026-02-14T13:43:34Z"
                },
                {
                    "text": "\ud83d\ude02\ud83d\ude02\ud83d\ude02\ud83d\ude02",
                    "author": "@Vivek-h3e3h",
                    "likes": 1,
                    "publishedAt": "2026-02-15T09:37:42Z"
                },
                {
                    "text": "\ud83d\ude05I'll look",
                    "author": "@KapilKumari-dv5ct",
                    "likes": 18,
                    "publishedAt": "2026-02-14T00:56:52Z"
                },
                {
                    "text": "\u0628\u0644\u064a\u0628\u0628\u064a\u062b\u0627\u0628\u0627\u062a\ud83d\ude02\u0645\u0631\u062d\u0628\u0627 \u0645\u0644\u064a\u0648\u0646 \u062f\u0648\u0644\u0627\u0631 \ud83d\ude02\ud83d\ude02\ud83d\ude02",
                    "author": "@\u0645\u062d\u0645\u0648\u062f\u0645\u0639\u062a\u0648\u0642-\u06412\u0630",
                    "likes": 2,
                    "publishedAt": "2026-02-15T09:31:22Z"
                }
            ]
        },
        {
            "fetchedAt": "20260215_220559",
            "commentCount": 6,
            "comments": [
                {
                    "text": "\ud83d\ude02\ud83d\ude02\ud83d\ude02\ud83d\ude02\ud83d\ude02\ud83d\ude02\ud83d\ude02\ud83d\ude02\ud83d\ude05\ud83d\ude05\ud83d\ude05\ud83d\ude05\ud83d\ude05\ud83d\ude05\ud83d\ude05",
                    "author": "@dominikawiktoria6665",
                    "likes": 1,
                    "publishedAt": "2026-02-15T18:18:11Z"
                },
                {
                    "text": "\ud83c\udf89\ud83d\ude22\ud83d\ude2e\ud83d\ude05\ud83d\ude0a",
                    "author": "@As-jz6to",
                    "likes": 3,
                    "publishedAt": "2026-02-15T14:27:52Z"
                },
                {
                    "text": "\u2764\u2764\u2764",
                    "author": "@FreefirMafia",
                    "likes": 5,
                    "publishedAt": "2026-02-14T13:43:34Z"
                },
                {
                    "text": "\u0628\u0644\u064a\u0628\u0628\u064a\u062b\u0627\u0628\u0627\u062a\ud83d\ude02\u0645\u0631\u062d\u0628\u0627 \u0645\u0644\u064a\u0648\u0646 \u062f\u0648\u0644\u0627\u0631 \ud83d\ude02\ud83d\ude02\ud83d\ude02",
                    "author": "@\u0645\u062d\u0645\u0648\u062f\u0645\u0639\u062a\u0648\u0642-\u06412\u0630",
                    "likes": 2,
                    "publishedAt": "2026-02-15T09:31:22Z"
                },
                {
                    "text": "\ud83d\ude02\ud83d\ude02\ud83d\ude02\ud83d\ude02",
                    "author": "@Vivek-h3e3h",
                    "likes": 5,
                    "publishedAt": "2026-02-15T09:37:42Z"
                },
                {
                    "text": "\ud83d\ude05I'll look",
                    "author": "@KapilKumari-dv5ct",
                    "likes": 21,
                    "publishedAt": "2026-02-14T00:56:52Z"
                }
            ]
        },
        {
            "fetchedAt": "20260216_191148",
            "commentCount": 8,
            "comments": [
                {
                    "text": "\ud83c\udf89\ud83d\ude22\ud83d\ude2e\ud83d\ude05\ud83d\ude0a",
                    "author": "@As-jz6to",
                    "likes": 13,
                    "publishedAt": "2026-02-15T14:27:52Z"
                },
                {
                    "text": "\ud83d\ude02\ud83d\ude02\ud83d\ude02\ud83d\ude02",
                    "author": "@Vivek-h3e3h",
                    "likes": 14,
                    "publishedAt": "2026-02-15T09:37:42Z"
                },
                {
                    "text": "\u0628\u0644\u064a\u0628\u0628\u064a\u062b\u0627\u0628\u0627\u062a\ud83d\ude02\u0645\u0631\u062d\u0628\u0627 \u0645\u0644\u064a\u0648\u0646 \u062f\u0648\u0644\u0627\u0631 \ud83d\ude02\ud83d\ude02\ud83d\ude02",
                    "author": "@\u0645\u062d\u0645\u0648\u062f\u0645\u0639\u062a\u0648\u0642-\u06412\u0630",
                    "likes": 5,
                    "publishedAt": "2026-02-15T09:31:22Z"
                },
                {
                    "text": "\ud83d\ude02\ud83d\ude02\ud83d\ude02\ud83d\ude02\ud83d\ude02\ud83d\ude02\ud83d\ude02\ud83d\ude02\ud83d\ude05\ud83d\ude05\ud83d\ude05\ud83d\ude05\ud83d\ude05\ud83d\ude05\ud83d\ude05",
                    "author": "@dominikawiktoria6665",
                    "likes": 13,
                    "publishedAt": "2026-02-15T18:18:11Z"
                },
                {
                    "text": "D by d\u2764\u2764\ud83d\ude02\ud83d\ude02",
                    "author": "@CotkarAyo-n8d",
                    "likes": 1,
                    "publishedAt": "2026-02-16T14:13:07Z"
                },
                {
                    "text": "\u2764\u2764\u2764",
                    "author": "@FreefirMafia",
                    "likes": 9,
                    "publishedAt": "2026-02-14T13:43:34Z"
                },
                {
                    "text": "\ud83d\ude05I'll look",
                    "author": "@KapilKumari-dv5ct",
                    "likes": 27,
                    "publishedAt": "2026-02-14T00:56:52Z"
                },
                {
                    "text": "\u2764\u2764\u2764",
                    "author": "@\u0627\u062d\u0645\u062f\u0627\u0628\u0648\u062e\u0627\u0644\u062f-\u06375\u0633",
                    "likes": 1,
                    "publishedAt": "2026-02-16T06:32:20Z"
                }
            ]
        },
        {
            "fetchedAt": "20260217_181951",
            "commentCount": 9,
            "comments": [
                {
                    "text": "\ud83c\udf89\ud83d\ude22\ud83d\ude2e\ud83d\ude05\ud83d\ude0a",
                    "author": "@As-jz6to",
                    "likes": 15,
                    "publishedAt": "2026-02-15T14:27:52Z"
                },
                {
                    "text": "J",
                    "author": "@jawadkhan-w2o4m",
                    "likes": 0,
                    "publishedAt": "2026-02-17T13:22:23Z"
                },
                {
                    "text": "\ud83d\ude02\ud83d\ude02\ud83d\ude02\ud83d\ude02",
                    "author": "@Vivek-h3e3h",
                    "likes": 20,
                    "publishedAt": "2026-02-15T09:37:42Z"
                },
                {
                    "text": "D by d\u2764\u2764\ud83d\ude02\ud83d\ude02",
                    "author": "@CotkarAyo-n8d",
                    "likes": 1,
                    "publishedAt": "2026-02-16T14:13:07Z"
                },
                {
                    "text": "\u0628\u0644\u064a\u0628\u0628\u064a\u062b\u0627\u0628\u0627\u062a\ud83d\ude02\u0645\u0631\u062d\u0628\u0627 \u0645\u0644\u064a\u0648\u0646 \u062f\u0648\u0644\u0627\u0631 \ud83d\ude02\ud83d\ude02\ud83d\ude02",
                    "author": "@\u0645\u062d\u0645\u0648\u062f\u0645\u0639\u062a\u0648\u0642-\u06412\u0630",
                    "likes": 6,
                    "publishedAt": "2026-02-15T09:31:22Z"
                },
                {
                    "text": "\u2764\u2764\u2764",
                    "author": "@FreefirMafia",
                    "likes": 9,
                    "publishedAt": "2026-02-14T13:43:34Z"
                },
                {
                    "text": "\ud83d\ude05I'll look",
                    "author": "@KapilKumari-dv5ct",
                    "likes": 31,
                    "publishedAt": "2026-02-14T00:56:52Z"
                },
                {
                    "text": "\ud83d\ude02\ud83d\ude02\ud83d\ude02\ud83d\ude02\ud83d\ude02\ud83d\ude02\ud83d\ude02\ud83d\ude02\ud83d\ude05\ud83d\ude05\ud83d\ude05\ud83d\ude05\ud83d\ude05\ud83d\ude05\ud83d\ude05",
                    "author": "@dominikawiktoria6665",
                    "likes": 13,
                    "publishedAt": "2026-02-15T18:18:11Z"
                },
                {
                    "text": "\u2764\u2764\u2764",
                    "author": "@\u0627\u062d\u0645\u062f\u0627\u0628\u0648\u062e\u0627\u0644\u062f-\u06375\u0633",
                    "likes": 1,
                    "publishedAt": "2026-02-16T06:32:20Z"
                }
            ]
        },
        {
            "fetchedAt": "20260219_031658",
            "commentCount": 10,
            "comments": [
                {
                    "text": "\ud83c\udf89\ud83d\ude22\ud83d\ude2e\ud83d\ude05\ud83d\ude0a",
                    "author": "@As-jz6to",
                    "likes": 19,
                    "publishedAt": "2026-02-15T14:27:52Z"
                },
                {
                    "text": "\ud83d\ude02\ud83d\ude02\ud83d\ude02\ud83d\ude02",
                    "author": "@Vivek-h3e3h",
                    "likes": 22,
                    "publishedAt": "2026-02-15T09:37:42Z"
                },
                {
                    "text": "No",
                    "author": "@Yashparjapati1994",
                    "likes": 0,
                    "publishedAt": "2026-02-19T02:54:15Z"
                },
                {
                    "text": "D by d\u2764\u2764\ud83d\ude02\ud83d\ude02",
                    "author": "@CotkarAyo-n8d",
                    "likes": 2,
                    "publishedAt": "2026-02-16T14:13:07Z"
                },
                {
                    "text": "J",
                    "author": "@jawadkhan-w2o4m",
                    "likes": 0,
                    "publishedAt": "2026-02-17T13:22:23Z"
                },
                {
                    "text": "\u0628\u0644\u064a\u0628\u0628\u064a\u062b\u0627\u0628\u0627\u062a\ud83d\ude02\u0645\u0631\u062d\u0628\u0627 \u0645\u0644\u064a\u0648\u0646 \u062f\u0648\u0644\u0627\u0631 \ud83d\ude02\ud83d\ude02\ud83d\ude02",
                    "author": "@\u0645\u062d\u0645\u0648\u062f\u0645\u0639\u062a\u0648\u0642-\u06412\u0630",
                    "likes": 6,
                    "publishedAt": "2026-02-15T09:31:22Z"
                },
                {
                    "text": "\ud83d\ude05I'll look",
                    "author": "@KapilKumari-dv5ct",
                    "likes": 34,
                    "publishedAt": "2026-02-14T00:56:52Z"
                },
                {
                    "text": "\u2764\u2764\u2764",
                    "author": "@FreefirMafia",
                    "likes": 9,
                    "publishedAt": "2026-02-14T13:43:34Z"
                },
                {
                    "text": "\ud83d\ude02\ud83d\ude02\ud83d\ude02\ud83d\ude02\ud83d\ude02\ud83d\ude02\ud83d\ude02\ud83d\ude02\ud83d\ude05\ud83d\ude05\ud83d\ude05\ud83d\ude05\ud83d\ude05\ud83d\ude05\ud83d\ude05",
                    "author": "@dominikawiktoria6665",
                    "likes": 13,
                    "publishedAt": "2026-02-15T18:18:11Z"
                },
                {
                    "text": "\u2764\u2764\u2764",
                    "author": "@\u0627\u062d\u0645\u062f\u0627\u0628\u0648\u062e\u0627\u0644\u062f-\u06375\u0633",
                    "likes": 1,
                    "publishedAt": "2026-02-16T06:32:20Z"
                }
            ]
        }
    ]
}