{
    "videoId": "qnkymjYA3vs",
    "history": [
        {
            "fetchedAt": "20260216_214030",
            "commentCount": 2,
            "comments": [
                {
                    "text": "Tiki tiki \u2764",
                    "author": "@TerezinhaFreitas-v8g",
                    "likes": 0,
                    "publishedAt": "2026-02-16T20:50:03Z"
                },
                {
                    "text": "\u2764\u2764\u2764\u2764\u2764",
                    "author": "@\u0422\u0438\u043c\u043e\u0445\u0430100",
                    "likes": 1,
                    "publishedAt": "2026-02-16T18:38:36Z"
                }
            ]
        }
    ]
}