{
    "videoId": "tC6L-VlZFfU",
    "history": [
        {
            "fetchedAt": "20260217_182218",
            "commentCount": 0,
            "comments": []
        },
        {
            "fetchedAt": "20260225_080437",
            "commentCount": 1,
            "comments": [
                {
                    "text": "2nd picture is so pretty",
                    "author": "@Littleponki-g4t",
                    "likes": 0,
                    "publishedAt": "2026-02-24T11:54:56Z"
                }
            ]
        }
    ]
}