{
    "videoId": "IrgvHqyO-Ko",
    "history": [
        {
            "fetchedAt": "20260215_220739",
            "commentCount": 25,
            "comments": [
                {
                    "text": "Its 0 because 1-2 is -1 and -1+1 is 0",
                    "author": "@Dinoloverandhi",
                    "likes": 3,
                    "publishedAt": "2026-02-15T21:52:48Z"
                },
                {
                    "text": "respuesta 0A",
                    "author": "@JuanmanuelVqzwuez",
                    "likes": 1,
                    "publishedAt": "2026-02-15T21:55:36Z"
                },
                {
                    "text": "2\ud83d\ude2e",
                    "author": "@\u0438\u0432\u0430\u043d\u043d\u043e\u0432\u0438\u043a\u043e\u0432-\u043b8\u044e",
                    "likes": 1,
                    "publishedAt": "2026-02-15T21:47:56Z"
                },
                {
                    "text": "3 por qu\u00e9 el uno no le puede sacar el dos",
                    "author": "@MatheoNicolasCasta\u00f1eda",
                    "likes": 1,
                    "publishedAt": "2026-02-15T21:51:18Z"
                },
                {
                    "text": "Essssssssss bos\ud83c\udf89\ud83c\udf89",
                    "author": "@palomamendez6538",
                    "likes": 1,
                    "publishedAt": "2026-02-15T21:42:17Z"
                },
                {
                    "text": "0\u2764",
                    "author": "@adrianacandido1390",
                    "likes": 0,
                    "publishedAt": "2026-02-15T22:06:47Z"
                },
                {
                    "text": "La repuesta es el 2",
                    "author": "@Sebasti\u00e1nAray-l3y",
                    "likes": 0,
                    "publishedAt": "2026-02-15T22:06:14Z"
                },
                {
                    "text": "2 cause PEMDAS addition then subtraction",
                    "author": "@Micaela-px5qb",
                    "likes": 1,
                    "publishedAt": "2026-02-15T21:42:28Z"
                },
                {
                    "text": "Calculen bien es 2",
                    "author": "@IANMolina-q8f",
                    "likes": 1,
                    "publishedAt": "2026-02-15T21:39:50Z"
                },
                {
                    "text": "2",
                    "author": "@\u0412\u0430\u043b\u0435\u043d\u0442\u0438\u043d\u0430\u041f\u043e\u043f\u043a\u043e\u0432\u0430-\u043a1\u0443",
                    "likes": 10,
                    "publishedAt": "2026-02-15T17:08:32Z"
                },
                {
                    "text": "Fa 0",
                    "author": "@fildadehima2146",
                    "likes": 2,
                    "publishedAt": "2026-02-15T21:51:03Z"
                },
                {
                    "text": "\u064a\u0633\u0627\u0648\u064a 0",
                    "author": "@\u0627\u0645\u062d\u0633\u064a\u0646-\u06375\u06454\u0632",
                    "likes": 2,
                    "publishedAt": "2026-02-15T21:02:03Z"
                },
                {
                    "text": "\u0662",
                    "author": "@\u064a\u0648\u0633\u0641\u0627\u0644\u0639\u0631\u0627\u0642\u064a-\u064a3\u06345\u063a",
                    "likes": 0,
                    "publishedAt": "2026-02-15T22:03:14Z"
                },
                {
                    "text": "1-2+1= 0",
                    "author": "@wissal-c3x45",
                    "likes": 3,
                    "publishedAt": "2026-02-15T20:23:30Z"
                },
                {
                    "text": "Easy its 0 1-2 = -1 + 1 = 0",
                    "author": "@JoshuaMCoolKing",
                    "likes": 2,
                    "publishedAt": "2026-02-15T21:06:11Z"
                },
                {
                    "text": "es dos por que 2 + 1 =3 y - 1 es igual a 2 los que dicen 3 est\u00e1n incorrectos que los manden a kinder",
                    "author": "@AnaCervantes-g9h",
                    "likes": 1,
                    "publishedAt": "2026-02-15T21:44:01Z"
                },
                {
                    "text": "1-2+1= 2",
                    "author": "@AleidaBance-m4m",
                    "likes": 0,
                    "publishedAt": "2026-02-15T21:59:37Z"
                },
                {
                    "text": "U can do 1-2",
                    "author": "@georgewegg3540",
                    "likes": 6,
                    "publishedAt": "2026-02-15T19:22:57Z"
                },
                {
                    "text": "1-2=0",
                    "author": "@\u0414\u0430\u0432\u0438\u0434\u0422\u043e\u0440\u043e\u0441\u044f\u043d-\u04421\u043f",
                    "likes": 3,
                    "publishedAt": "2026-02-15T17:25:19Z"
                },
                {
                    "text": "0",
                    "author": "@adelanunez9758",
                    "likes": 10,
                    "publishedAt": "2026-02-15T17:18:27Z"
                },
                {
                    "text": "1",
                    "author": "@JonathanHernandez-b5t",
                    "likes": 2,
                    "publishedAt": "2026-02-15T17:28:06Z"
                },
                {
                    "text": "Aki los que dicen 0",
                    "author": "@adelanunez9758",
                    "likes": 5,
                    "publishedAt": "2026-02-15T17:18:46Z"
                },
                {
                    "text": "Es 0 xquee\nEx: 1-2= -1\n-1+1=0",
                    "author": "@ezeprimerj",
                    "likes": 2,
                    "publishedAt": "2026-02-15T17:41:52Z"
                },
                {
                    "text": "1+1-2=0",
                    "author": "@\u041a\u0438\u0440\u0438\u043b\u0426\u0432\u0435\u0442\u043a\u043e\u0432-\u04331\u0435",
                    "likes": 2,
                    "publishedAt": "2026-02-15T19:32:28Z"
                },
                {
                    "text": "1-2+1=2\ud83d\ude0a",
                    "author": "@kalpacsmiri",
                    "likes": 3,
                    "publishedAt": "2026-02-15T19:31:34Z"
                }
            ]
        }
    ]
}